chipi_python-1.0.0.dist-info/licenses/LICENSE
chipi_sdk/__init__.py
chipi_sdk/client.py
chipi_sdk/constants.py
chipi_sdk/encryption.py
chipi_sdk/errors.py
chipi_sdk/execute_paymaster.py
chipi_sdk/formatters.py
chipi_sdk/py.typed
chipi_sdk/sdk.py
chipi_sdk/sessions.py
chipi_sdk/sku_transactions.py
chipi_sdk/skus.py
chipi_sdk/transactions.py
chipi_sdk/users.py
chipi_sdk/validators.py
chipi_sdk/wallets.py
chipi_sdk/models/__init__.py
chipi_sdk/models/core.py
chipi_sdk/models/session.py
chipi_sdk/models/sku.py
chipi_sdk/models/sku_transaction.py
chipi_sdk/models/transaction.py
chipi_sdk/models/user.py
chipi_sdk/models/wallet.py
chipi_python-1.0.0.dist-info/METADATA
chipi_python-1.0.0.dist-info/WHEEL
chipi_python-1.0.0.dist-info/top_level.txt
chipi_python-1.0.0.dist-info/RECORD
