Metadata-Version: 2.4
Name: chipi-python
Version: 1.0.0
Summary: Python SDK for Starknet Gasless Transactions via Chipi
Author-email: Chipi Pay <support@chipipay.com>
License: MIT
Project-URL: Homepage, https://github.com/chipi-pay/chipi-sdk
Project-URL: Documentation, https://docs.chipipay.com
Project-URL: Repository, https://github.com/chipi-pay/chipi-sdk
Project-URL: Issues, https://github.com/chipi-pay/chipi-sdk/issues
Keywords: starknet,blockchain,gasless,transactions,web3,chipi,paymaster
Classifier: Development Status :: 4 - Beta
Classifier: Intended Audience :: Developers
Classifier: License :: OSI Approved :: MIT License
Classifier: Programming Language :: Python :: 3
Classifier: Programming Language :: Python :: 3.11
Classifier: Programming Language :: Python :: 3.12
Classifier: Topic :: Software Development :: Libraries :: Python Modules
Classifier: Topic :: Internet
Classifier: Topic :: Software Development
Requires-Python: >=3.11
License-File: LICENSE
Requires-Dist: starknet-py>=0.23.0
Requires-Dist: pydantic>=2.0.0
Requires-Dist: httpx>=0.27.0
Requires-Dist: cryptography>=42.0.0
Requires-Dist: typing-extensions>=4.9.0
Provides-Extra: dev
Requires-Dist: pytest>=8.0.0; extra == "dev"
Requires-Dist: pytest-asyncio>=0.23.0; extra == "dev"
Requires-Dist: pytest-cov>=4.1.0; extra == "dev"
Requires-Dist: pytest-mock>=3.12.0; extra == "dev"
Requires-Dist: black>=24.0.0; extra == "dev"
Requires-Dist: ruff>=0.3.0; extra == "dev"
Requires-Dist: mypy>=1.8.0; extra == "dev"
Requires-Dist: build>=1.0.0; extra == "dev"
Requires-Dist: twine>=5.0.0; extra == "dev"
Dynamic: license-file
